{
  "POIs": [
    {
      "fit": [
        -0.16451483964920044,
        0.0,
        0.16442078351974487
      ],
      "name": "r"
    }
  ],
  "method": "default",
  "params": [
    {
      "fit": [
        -0.9938687682151794,
        0.0,
        0.9943541288375854
      ],
      "groups": [],
      "impact_r": 1.890389648906421e-05,
      "name": "BR_htt_PU_alphas",
      "prefit": [
        -0.9999999999999999,
        0.0,
        0.9999999999999999
      ],
      "r": [
        1.668314689595718e-05,
        0.0,
        -1.890389648906421e-05
      ],
      "type": "Gaussian"
    },
    {
      "fit": [
        -0.9938713312149048,
        0.0,
        0.9943516850471497
      ],
      "groups": [],
      "impact_r": 2.9631035431521013e-05,
      "name": "BR_htt_PU_mq",
      "prefit": [
        -0.9999999999999999,
        0.0,
        0.9999999999999999
      ],
      "r": [
        2.708132342377212e-05,
        0.0,
        -2.9631035431521013e-05
      ],
      "type": "Gaussian"
    },
    {
      "fit": [
        -0.9938777685165405,
        0.0,
        0.994346022605896
      ],
      "groups": [],
      "impact_r": 9.466308256378397e-05,
      "name": "BR_htt_THU",
      "prefit": [
        -0.9999999999999999,
        0.0,
        0.9999999999999999
      ],
      "r": [
        8.292718848679215e-05,
        0.0,
        -9.466308256378397e-05
      ],
      "type": "Gaussian"
    },
    {
      "fit": [
        -0.9938669800758362,
        0.0,
        0.9943556189537048
      ],
      "groups": [],
      "impact_r": 1.237816718457907e-06,
      "name": "BR_hww_PU_alphas",
      "prefit": [
        -0.9999999999999999,
        0.0,
        0.9999999999999999
      ],
      "r": [
        -1.226204403792508e-06,
        0.0,
        -1.237816718457907e-06
      ],
      "type": "Gaussian"
    },
    {
      "fit": [
        -0.993867039680481,
        0.0,
        0.9943556189537048
      ],
      "groups": [],
      "impact_r": 1.23104939575569e-06,
      "name": "BR_hww_PU_mq",
      "prefit": [
        -0.9999999999999999,
        0.0,
        0.9999999999999999
      ],
      "r": [
        -1.1801206483141868e-06,
        0.0,
        -1.23104939575569e-06
      ],
      "type": "Gaussian"
    },
    {
      "fit": [
        -0.993867039680481,
        0.0,
        0.9943556189537048
      ],
      "groups": [],
      "impact_r": 1.2311262480579899e-06,
      "name": "BR_hww_THU",
      "prefit": [
        -0.9999999999999999,
        0.0,
        0.9999999999999999
      ],
      "r": [
        -1.180126332656073e-06,
        0.0,
        -1.2311262480579899e-06
      ],
      "type": "Gaussian"
    },
    {
      "fit": [
        -0.9939854145050049,
        0.0,
        0.9939242005348206
      ],
      "groups": [],
      "impact_r": 0.002287793206050992,
      "name": "CMS_DYpTreweight_2018_13TeV",
      "prefit": [
        -1.0,
        0.0,
        1.0
      ],
      "r": [
        0.0019831822719424963,
        0.0,
        -0.002287793206050992
      ],
      "type": "Gaussian"
    },
    {
      "fit": [
        -0.9717587232589722,
        0.0,
        0.9663277268409729
      ],
      "groups": [],
      "impact_r": 0.020707860589027405,
      "name": "CMS_Jer_2018_13TeV",
      "prefit": [
        -1.0,
        0.0,
        1.0
      ],
      "r": [
        0.000466078839963302,
        0.0,
        0.020707860589027405
      ],
      "type": "Gaussian"
    },
    {
      "fit": [
        -0.9763662219047546,
        0.0,
        0.9737262725830078
      ],
      "groups": [],
      "impact_r": 0.012926332652568817,
      "name": "CMS_Jes_JetAbsolute_13TeV",
      "prefit": [
        -1.0,
        0.0,
        1.0
      ],
      "r": [
        -0.0033090761862695217,
        0.0,
        0.012926332652568817
      ],
      "type": "Gaussian"
    },
    {
      "fit": [
        -0.9891296625137329,
        0.0,
        0.9831955432891846
      ],
      "groups": [],
      "impact_r": 0.010820518247783184,
      "name": "CMS_Jes_JetAbsolute_2018_13TeV",
      "prefit": [
        -1.0,
        0.0,
        1.0
      ],
      "r": [
        -0.005348000675439835,
        0.0,
        0.010820518247783184
      ],
      "type": "Gaussian"
    },
    {
      "fit": [
        -0.985709547996521,
        0.0,
        0.9853448867797852
      ],
      "groups": [],
      "impact_r": 0.0005596154951490462,
      "name": "CMS_Jes_JetBBEC1_13TeV",
      "prefit": [
        -1.0,
        0.0,
        1.0
      ],
      "r": [
        -0.00033487213659100235,
        0.0,
        0.0005596154951490462
      ],
      "type": "Gaussian"
    },
    {
      "fit": [
        -0.989169180393219,
        0.0,
        0.9831573963165283
      ],
      "groups": [],
      "impact_r": 0.004807505756616592,
      "name": "CMS_Jes_JetBBEC1_2018_13TeV",
      "prefit": [
        -1.0,
        0.0,
        1.0
      ],
      "r": [
        -0.004807505756616592,
        0.0,
        0.0009878264972940087
      ],
      "type": "Gaussian"
    },
    {
      "fit": [
        -0.9862017631530762,
        0.0,
        0.987197756767273
      ],
      "groups": [],
      "impact_r": 0.0023899441584944725,
      "name": "CMS_Jes_JetEC2_13TeV",
      "prefit": [
        -1.0,
        0.0,
        1.0
      ],
      "r": [
        -0.0023899441584944725,
        0.0,
        -0.0003276694333180785
      ],
      "type": "Gaussian"
    },
    {
      "fit": [
        -0.9874992966651917,
        0.0,
        0.9836038947105408
      ],
      "groups": [],
      "impact_r": 0.0033270213752985,
      "name": "CMS_Jes_JetEC2_2018_13TeV",
      "prefit": [
        -1.0,
        0.0,
        1.0
      ],
      "r": [
        -0.0033270213752985,
        0.0,
        -0.001892597763799131
      ],
      "type": "Gaussian"
    },
    {
      "fit": [
        -0.9862523078918457,
        0.0,
        0.9773017764091492
      ],
      "groups": [],
      "impact_r": 0.01538549643009901,
      "name": "CMS_Jes_JetFlavorQCD_13TeV",
      "prefit": [
        -1.0,
        0.0,
        1.0
      ],
      "r": [
        -0.0117300134152174,
        0.0,
        0.01538549643009901
      ],
      "type": "Gaussian"
    },
    {
      "fit": [
        -0.9858358502388,
        0.0,
        0.9795655608177185
      ],
      "groups": [],
      "impact_r": 0.00887349620461464,
      "name": "CMS_Jes_JetHF_13TeV",
      "prefit": [
        -1.0,
        0.0,
        1.0
      ],
      "r": [
        -0.00887349620461464,
        0.0,
        -0.0011812096927314997
      ],
      "type": "Gaussian"
    },
    {
      "fit": [
        -0.9829007983207703,
        0.0,
        0.9825531244277954
      ],
      "groups": [],
      "impact_r": 0.007577447686344385,
      "name": "CMS_Jes_JetHF_2018_13TeV",
      "prefit": [
        -1.0,
        0.0,
        1.0
      ],
      "r": [
        -0.004121985752135515,
        0.0,
        -0.007577447686344385
      ],
      "type": "Gaussian"
    },
    {
      "fit": [
        -0.9744167923927307,
        0.0,
        0.9806569814682007
      ],
      "groups": [],
      "impact_r": 0.010583682917058468,
      "name": "CMS_Jes_JetRelativeBal_13TeV",
      "prefit": [
        -1.0,
        0.0,
        1.0
      ],
      "r": [
        0.004902251996099949,
        0.0,
        -0.010583682917058468
      ],
      "type": "Gaussian"
    },
    {
      "fit": [
        -0.9729816913604736,
        0.0,
        0.9773254990577698
      ],
      "groups": [],
      "impact_r": 0.012581144459545612,
      "name": "CMS_Jes_JetRelativeSample_13TeV",
      "prefit": [
        -1.0,
        0.0,
        1.0
      ],
      "r": [
        0.010577881708741188,
        0.0,
        -0.012581144459545612
      ],
      "type": "Gaussian"
    },
    {
      "fit": [
        -0.9797171950340271,
        0.0,
        0.9851062893867493
      ],
      "groups": [],
      "impact_r": 0.012544644065201283,
      "name": "CMS_MET_chargedUes_13TeV",
      "prefit": [
        -1.0,
        0.0,
        1.0
      ],
      "r": [
        -0.012544644065201283,
        0.0,
        -0.0005536127719096839
      ],
      "type": "Gaussian"
    },
    {
      "fit": [
        -0.9851889610290527,
        0.0,
        0.9835333228111267
      ],
      "groups": [],
      "impact_r": 0.002955540083348751,
      "name": "CMS_MET_ecalUes_13TeV",
      "prefit": [
        -1.0,
        0.0,
        1.0
      ],
      "r": [
        0.002955540083348751,
        0.0,
        0.0009654278983362019
      ],
      "type": "Gaussian"
    },
    {
      "fit": [
        -0.9488257169723511,
        0.0,
        0.966362714767456
      ],
      "groups": [],
      "impact_r": 0.00783614907413721,
      "name": "CMS_MET_hcalUes_13TeV",
      "prefit": [
        -1.0,
        0.0,
        1.0
      ],
      "r": [
        0.0063600786961615086,
        0.0,
        0.00783614907413721
      ],
      "type": "Gaussian"
    },
    {
      "fit": [
        -0.961155116558075,
        0.0,
        0.9815986752510071
      ],
      "groups": [],
      "impact_r": 0.012792034074664116,
      "name": "CMS_MET_hfUes_13TeV",
      "prefit": [
        -1.0,
        0.0,
        1.0
      ],
      "r": [
        0.012792034074664116,
        0.0,
        0.004070816561579704
      ],
      "type": "Gaussian"
    },
    {
      "fit": [
        -0.9645980000495911,
        0.0,
        0.9661633968353271
      ],
      "groups": [],
      "impact_r": 0.00791669450700283,
      "name": "CMS_Pileup_13TeV",
      "prefit": [
        -1.0,
        0.0,
        1.0
      ],
      "r": [
        -0.007521074265241623,
        0.0,
        0.00791669450700283
      ],
      "type": "Gaussian"
    },
    {
      "fit": [
        -0.9353715181350708,
        0.0,
        0.9352630376815796
      ],
      "groups": [],
      "impact_r": 0.002161037642508745,
      "name": "CMS_Trigger_emb_mutauh_2018_13TeV",
      "prefit": [
        -0.9999999999999999,
        0.0,
        0.9999999999999999
      ],
      "r": [
        -0.002161037642508745,
        0.0,
        0.0019681218545883894
      ],
      "type": "Gaussian"
    },
    {
      "fit": [
        -0.987857460975647,
        0.0,
        0.9875011444091797
      ],
      "groups": [],
      "impact_r": 0.007746623829007149,
      "name": "CMS_Trigger_mutauh_2018_13TeV",
      "prefit": [
        -0.9999999999999999,
        0.0,
        0.9999999999999999
      ],
      "r": [
        -0.007746623829007149,
        0.0,
        0.007338306866586208
      ],
      "type": "Gaussian"
    },
    {
      "fit": [
        -0.9939472079277039,
        0.0,
        0.9939550161361694
      ],
      "groups": [],
      "impact_r": 0.0022599538788199425,
      "name": "CMS_eff_btag_2018_13TeV",
      "prefit": [
        -1.0,
        0.0,
        1.0
      ],
      "r": [
        0.0022599538788199425,
        0.0,
        -0.0003514945856295526
      ],
      "type": "Gaussian"
    },
    {
      "fit": [
        -0.9504112005233765,
        0.0,
        0.9502512216567993
      ],
      "groups": [],
      "impact_r": 0.0018523053731769323,
      "name": "CMS_eff_emb_m",
      "prefit": [
        -0.9999999999999999,
        0.0,
        0.9999999999999999
      ],
      "r": [
        -0.0018523053731769323,
        0.0,
        0.0016357413260266185
      ],
      "type": "Gaussian"
    },
    {
      "fit": [
        -0.8849809765815735,
        0.0,
        0.8808239102363586
      ],
      "groups": [],
      "impact_r": 0.003286437364295125,
      "name": "CMS_emb_tauid_pt30to35_2018_13TeV",
      "prefit": [
        -1.0,
        0.0,
        1.0
      ],
      "r": [
        -0.003212554380297661,
        0.0,
        0.003286437364295125
      ],
      "type": "Gaussian"
    },
    {
      "fit": [
        -0.9250122904777527,
        0.0,
        0.9404219388961792
      ],
      "groups": [],
      "impact_r": 0.0009820850100368261,
      "name": "CMS_emb_tauid_ptgt40_2018_13TeV",
      "prefit": [
        -1.0,
        0.0,
        1.0
      ],
      "r": [
        0.0009820850100368261,
        0.0,
        -0.0009516953723505139
      ],
      "type": "Gaussian"
    },
    {
      "fit": [
        -0.9940940737724304,
        0.0,
        0.9943768978118896
      ],
      "groups": [],
      "impact_r": 9.923010111378971e-06,
      "name": "CMS_etauFR_barrel_2018_13TeV",
      "prefit": [
        -1.0,
        0.0,
        1.0
      ],
      "r": [
        2.2926865312911104e-06,
        0.0,
        -9.923010111378971e-06
      ],
      "type": "Gaussian"
    },
    {
      "fit": [
        -0.9940896034240723,
        0.0,
        0.9943816065788269
      ],
      "groups": [],
      "impact_r": 1.2553310625662562e-05,
      "name": "CMS_etauFR_endcap_2018_13TeV",
      "prefit": [
        -1.0,
        0.0,
        1.0
      ],
      "r": [
        1.0499503332539462e-05,
        0.0,
        -1.2553310625662562e-05
      ],
      "type": "Gaussian"
    },
    {
      "fit": [
        -0.9858847260475159,
        0.0,
        0.9860134720802307
      ],
      "groups": [],
      "impact_r": 0.008699219673871994,
      "name": "CMS_lumi_2018_13TeV",
      "prefit": [
        -0.9999999999999999,
        0.0,
        0.9999999999999999
      ],
      "r": [
        -0.008699219673871994,
        0.0,
        0.007979966700077057
      ],
      "type": "Gaussian"
    },
    {
      "fit": [
        -0.9940503835678101,
        0.0,
        0.994164764881134
      ],
      "groups": [],
      "impact_r": 0.0008969949558377266,
      "name": "CMS_lumi_beam-beam-deflection_13TeV",
      "prefit": [
        -0.9999999999999999,
        0.0,
        0.9999999999999999
      ],
      "r": [
        -0.0008969949558377266,
        0.0,
        0.00016370482626371086
      ],
      "type": "Gaussian"
    },
    {
      "fit": [
        -0.9932611584663391,
        0.0,
        0.9939079284667969
      ],
      "groups": [],
      "impact_r": 0.0023800809867680073,
      "name": "CMS_lumi_dynamic-beta_13TeV",
      "prefit": [
        -0.9999999999999999,
        0.0,
        0.9999999999999999
      ],
      "r": [
        -0.0023800809867680073,
        0.0,
        0.0006006028852425516
      ],
      "type": "Gaussian"
    },
    {
      "fit": [
        -0.994072675704956,
        0.0,
        0.994164764881134
      ],
      "groups": [],
      "impact_r": 0.0008921158732846379,
      "name": "CMS_lumi_ghosts-satellites_13TeV",
      "prefit": [
        -0.9999999999999999,
        0.0,
        0.9999999999999999
      ],
      "r": [
        -0.0008921158732846379,
        0.0,
        0.0001625441072974354
      ],
      "type": "Gaussian"
    },
    {
      "fit": [
        -0.9927355051040649,
        0.0,
        0.993048906326294
      ],
      "groups": [],
      "impact_r": 0.0034993488807231188,
      "name": "CMS_lumi_xy-factorization_13TeV",
      "prefit": [
        -0.9999999999999999,
        0.0,
        0.9999999999999999
      ],
      "r": [
        -0.0034993488807231188,
        0.0,
        0.0031877816654741764
      ],
      "type": "Gaussian"
    },
    {
      "fit": [
        -0.9689670205116272,
        0.0,
        0.9720884561538696
      ],
      "groups": [],
      "impact_r": 0.02008862793445587,
      "name": "CMS_muFR_p0_2018_13TeV",
      "prefit": [
        -1.0,
        0.0,
        1.0
      ],
      "r": [
        -0.009673905558884144,
        0.0,
        0.02008862793445587
      ],
      "type": "Gaussian"
    },
    {
      "fit": [
        -0.9675776958465576,
        0.0,
        0.9707444906234741
      ],
      "groups": [],
      "impact_r": 0.004736288450658321,
      "name": "CMS_muFR_p1_2018_13TeV",
      "prefit": [
        -1.0,
        0.0,
        1.0
      ],
      "r": [
        0.004029285628348589,
        0.0,
        0.004736288450658321
      ],
      "type": "Gaussian"
    },
    {
      "fit": [
        -0.976362407207489,
        0.0,
        0.9766232967376709
      ],
      "groups": [],
      "impact_r": 0.015740906819701195,
      "name": "CMS_mutauFR_eta0p4to0p8_2018_13TeV",
      "prefit": [
        -1.0,
        0.0,
        1.0
      ],
      "r": [
        -0.015740906819701195,
        0.0,
        0.014880737289786339
      ],
      "type": "Gaussian"
    },
    {
      "fit": [
        -0.9731534123420715,
        0.0,
        0.973679780960083
      ],
      "groups": [],
      "impact_r": 0.015665806829929352,
      "name": "CMS_mutauFR_eta0p8to1p2_2018_13TeV",
      "prefit": [
        -1.0,
        0.0,
        1.0
      ],
      "r": [
        -0.015665806829929352,
        0.0,
        0.014643915928900242
      ],
      "type": "Gaussian"
    },
    {
      "fit": [
        -0.9711947441101074,
        0.0,
        0.9723818898200989
      ],
      "groups": [],
      "impact_r": 0.017346933484077454,
      "name": "CMS_mutauFR_eta1p2to1p7_2018_13TeV",
      "prefit": [
        -1.0,
        0.0,
        1.0
      ],
      "r": [
        -0.017346933484077454,
        0.0,
        0.01615053415298462
      ],
      "type": "Gaussian"
    },
    {
      "fit": [
        -0.9538986682891846,
        0.0,
        0.9569011926651001
      ],
      "groups": [],
      "impact_r": 0.025887466967105865,
      "name": "CMS_mutauFR_etaGt1p7_2018_13TeV",
      "prefit": [
        -1.0,
        0.0,
        1.0
      ],
      "r": [
        -0.025887466967105865,
        0.0,
        0.024464339017868042
      ],
      "type": "Gaussian"
    },
    {
      "fit": [
        -0.9624337553977966,
        0.0,
        0.9639115929603577
      ],
      "groups": [],
      "impact_r": 0.018833652138710022,
      "name": "CMS_mutauFR_etaLt0p4_2018_13TeV",
      "prefit": [
        -1.0,
        0.0,
        1.0
      ],
      "r": [
        -0.018833652138710022,
        0.0,
        0.017553582787513733
      ],
      "type": "Gaussian"
    },
    {
      "fit": [
        -0.8424064517021179,
        0.0,
        0.8804270029067993
      ],
      "groups": [],
      "impact_r": 0.023655664175748825,
      "name": "CMS_reso_met_0Jet_2018_13TeV",
      "prefit": [
        -1.0,
        0.0,
        1.0
      ],
      "r": [
        -0.023655664175748825,
        0.0,
        -0.016730375587940216
      ],
      "type": "Gaussian"
    },
    {
      "fit": [
        -0.9940868020057678,
        0.0,
        0.9943844676017761
      ],
      "groups": [],
      "impact_r": 0.0,
      "name": "CMS_reso_met_1Jet_2018_13TeV",
      "prefit": [
        -1.0,
        0.0,
        1.0
      ],
      "r": [
        0.0,
        0.0,
        0.0
      ],
      "type": "Gaussian"
    },
    {
      "fit": [
        -0.9940868020057678,
        0.0,
        0.9943844676017761
      ],
      "groups": [],
      "impact_r": 0.0,
      "name": "CMS_reso_met_2Jet_2018_13TeV",
      "prefit": [
        -1.0,
        0.0,
        1.0
      ],
      "r": [
        0.0,
        0.0,
        0.0
      ],
      "type": "Gaussian"
    },
    {
      "fit": [
        -0.97535640001297,
        0.0,
        0.9528217315673828
      ],
      "groups": [],
      "impact_r": 0.014476236887276173,
      "name": "CMS_scale_emb_t_1prong1pizero_2018_13TeV",
      "prefit": [
        -1.0,
        0.0,
        1.0
      ],
      "r": [
        -0.010065772570669651,
        0.0,
        0.014476236887276173
      ],
      "type": "Gaussian"
    },
    {
      "fit": [
        -0.9852359890937805,
        0.0,
        0.9882504343986511
      ],
      "groups": [],
      "impact_r": 0.006379541475325823,
      "name": "CMS_scale_emb_t_1prong_2018_13TeV",
      "prefit": [
        -1.0,
        0.0,
        1.0
      ],
      "r": [
        -0.0006018522544763982,
        0.0,
        0.006379541475325823
      ],
      "type": "Gaussian"
    },
    {
      "fit": [
        -0.9928702116012573,
        0.0,
        0.9938198328018188
      ],
      "groups": [],
      "impact_r": 0.002858842955902219,
      "name": "CMS_scale_emb_t_3prong1pizero_2018_13TeV",
      "prefit": [
        -1.0,
        0.0,
        1.0
      ],
      "r": [
        -0.002858842955902219,
        0.0,
        0.00017322046915069222
      ],
      "type": "Gaussian"
    },
    {
      "fit": [
        -0.9893670082092285,
        0.0,
        0.9893956780433655
      ],
      "groups": [],
      "impact_r": 0.004469025880098343,
      "name": "CMS_scale_emb_t_3prong_2018_13TeV",
      "prefit": [
        -1.0,
        0.0,
        1.0
      ],
      "r": [
        -0.0026791763957589865,
        0.0,
        0.004469025880098343
      ],
      "type": "Gaussian"
    },
    {
      "fit": [
        -0.9934263825416565,
        0.0,
        0.9944433569908142
      ],
      "groups": [],
      "impact_r": 7.053402077872306e-05,
      "name": "CMS_scale_etauFR_barrel_1prong1pizero_2018_13TeV",
      "prefit": [
        -1.0,
        0.0,
        1.0
      ],
      "r": [
        7.053402077872306e-05,
        0.0,
        -6.811635103076696e-05
      ],
      "type": "Gaussian"
    },
    {
      "fit": [
        -0.9935301542282104,
        0.0,
        0.9942933917045593
      ],
      "groups": [],
      "impact_r": 9.93640351225622e-05,
      "name": "CMS_scale_etauFR_barrel_1prong_2018_13TeV",
      "prefit": [
        -1.0,
        0.0,
        1.0
      ],
      "r": [
        -6.412507354980335e-05,
        0.0,
        -9.93640351225622e-05
      ],
      "type": "Gaussian"
    },
    {
      "fit": [
        -0.9939427971839905,
        0.0,
        0.9940446615219116
      ],
      "groups": [],
      "impact_r": 0.000278462131973356,
      "name": "CMS_scale_etauFR_endcap_1prong1pizero_2018_13TeV",
      "prefit": [
        -1.0,
        0.0,
        1.0
      ],
      "r": [
        0.000278462131973356,
        0.0,
        0.00011807071859948337
      ],
      "type": "Gaussian"
    },
    {
      "fit": [
        -0.9935283660888672,
        0.0,
        0.9943370819091797
      ],
      "groups": [],
      "impact_r": 6.142299389466643e-05,
      "name": "CMS_scale_etauFR_endcap_1prong_2018_13TeV",
      "prefit": [
        -1.0,
        0.0,
        1.0
      ],
      "r": [
        -3.2438729249406606e-05,
        0.0,
        6.142299389466643e-05
      ],
      "type": "Gaussian"
    },
    {
      "fit": [
        -0.921297013759613,
        0.0,
        0.9521342515945435
      ],
      "groups": [],
      "impact_r": 0.019231602549552917,
      "name": "CMS_scale_m_eta1p2to2p1_13TeV",
      "prefit": [
        -1.0,
        0.0,
        1.0
      ],
      "r": [
        -0.0015721787931397557,
        0.0,
        -0.019231602549552917
      ],
      "type": "Gaussian"
    },
    {
      "fit": [
        -0.9190930128097534,
        0.0,
        0.8442080616950989
      ],
      "groups": [],
      "impact_r": 0.016181185841560364,
      "name": "CMS_scale_m_etaLt1p2_13TeV",
      "prefit": [
        -1.0,
        0.0,
        1.0
      ],
      "r": [
        -0.004231864120811224,
        0.0,
        -0.016181185841560364
      ],
      "type": "Gaussian"
    },
    {
      "fit": [
        -0.9298738241195679,
        0.0,
        0.9542335867881775
      ],
      "groups": [],
      "impact_r": 0.02238086611032486,
      "name": "CMS_scale_met_0Jet_2018_13TeV",
      "prefit": [
        -1.0,
        0.0,
        1.0
      ],
      "r": [
        -0.013884526677429676,
        0.0,
        -0.02238086611032486
      ],
      "type": "Gaussian"
    },
    {
      "fit": [
        -0.9940868020057678,
        0.0,
        0.9943844676017761
      ],
      "groups": [],
      "impact_r": 0.0,
      "name": "CMS_scale_met_1Jet_2018_13TeV",
      "prefit": [
        -1.0,
        0.0,
        1.0
      ],
      "r": [
        0.0,
        0.0,
        0.0
      ],
      "type": "Gaussian"
    },
    {
      "fit": [
        -0.9940868020057678,
        0.0,
        0.9943844676017761
      ],
      "groups": [],
      "impact_r": 0.0,
      "name": "CMS_scale_met_2Jet_2018_13TeV",
      "prefit": [
        -1.0,
        0.0,
        1.0
      ],
      "r": [
        0.0,
        0.0,
        0.0
      ],
      "type": "Gaussian"
    },
    {
      "fit": [
        -0.9316449165344238,
        0.0,
        0.881223201751709
      ],
      "groups": [],
      "impact_r": 0.013045836240053177,
      "name": "CMS_scale_mtauFR_1prong1pizero_2018_13TeV",
      "prefit": [
        -1.0,
        0.0,
        1.0
      ],
      "r": [
        0.009272018447518349,
        0.0,
        -0.013045836240053177
      ],
      "type": "Gaussian"
    },
    {
      "fit": [
        -0.9316883683204651,
        0.0,
        0.8812232613563538
      ],
      "groups": [],
      "impact_r": 0.01296808011829853,
      "name": "CMS_scale_mtauFR_1prong_2018_13TeV",
      "prefit": [
        -1.0,
        0.0,
        1.0
      ],
      "r": [
        0.009208747185766697,
        0.0,
        -0.01296808011829853
      ],
      "type": "Gaussian"
    },
    {
      "fit": [
        -0.9871922731399536,
        0.0,
        0.9788061380386353
      ],
      "groups": [],
      "impact_r": 0.012439905665814877,
      "name": "CMS_scale_t_1prong1pizero_2018_13TeV",
      "prefit": [
        -1.0,
        0.0,
        1.0
      ],
      "r": [
        -0.00547370221465826,
        0.0,
        0.012439905665814877
      ],
      "type": "Gaussian"
    },
    {
      "fit": [
        -0.9904355406761169,
        0.0,
        0.9881032109260559
      ],
      "groups": [],
      "impact_r": 0.00629348773509264,
      "name": "CMS_scale_t_1prong_2018_13TeV",
      "prefit": [
        -1.0,
        0.0,
        1.0
      ],
      "r": [
        -0.000547422852832824,
        0.0,
        0.00629348773509264
      ],
      "type": "Gaussian"
    },
    {
      "fit": [
        -0.992132842540741,
        0.0,
        0.9931010007858276
      ],
      "groups": [],
      "impact_r": 3.683096656459384e-05,
      "name": "CMS_scale_t_3prong1pizero_2018_13TeV",
      "prefit": [
        -1.0,
        0.0,
        1.0
      ],
      "r": [
        6.409793968487065e-06,
        0.0,
        -3.683096656459384e-05
      ],
      "type": "Gaussian"
    },
    {
      "fit": [
        -0.9895696043968201,
        0.0,
        0.9903044104576111
      ],
      "groups": [],
      "impact_r": 0.005001660902053118,
      "name": "CMS_scale_t_3prong_2018_13TeV",
      "prefit": [
        -1.0,
        0.0,
        1.0
      ],
      "r": [
        -0.005001660902053118,
        0.0,
        -0.0024874538648873568
      ],
      "type": "Gaussian"
    },
    {
      "fit": [
        -0.7412036657333374,
        0.0,
        0.7348884344100952
      ],
      "groups": [],
      "impact_r": 0.005406070500612259,
      "name": "CMS_selection_dimuon_emb_2018_13TeV",
      "prefit": [
        -0.9999999999999999,
        0.0,
        0.9999999999999999
      ],
      "r": [
        -0.005117704160511494,
        0.0,
        0.005406070500612259
      ],
      "type": "Gaussian"
    },
    {
      "fit": [
        -0.9941185116767883,
        0.0,
        0.9937297701835632
      ],
      "groups": [],
      "impact_r": 0.0017907187575474381,
      "name": "CMS_tauFR_p0_dm0_B_2018_13TeV",
      "prefit": [
        -1.0,
        0.0,
        1.0
      ],
      "r": [
        0.0004654594522435218,
        0.0,
        -0.0017907187575474381
      ],
      "type": "Gaussian"
    },
    {
      "fit": [
        -0.99375981092453,
        0.0,
        0.9933996796607971
      ],
      "groups": [],
      "impact_r": 0.0008990238420665264,
      "name": "CMS_tauFR_p0_dm0_E_2018_13TeV",
      "prefit": [
        -1.0,
        0.0,
        1.0
      ],
      "r": [
        -0.0002861802058760077,
        0.0,
        0.0008990238420665264
      ],
      "type": "Gaussian"
    },
    {
      "fit": [
        -0.9939226508140564,
        0.0,
        0.9939298629760742
      ],
      "groups": [],
      "impact_r": 0.001973066246137023,
      "name": "CMS_tauFR_p0_dm10_B_2018_13TeV",
      "prefit": [
        -1.0,
        0.0,
        1.0
      ],
      "r": [
        0.001973066246137023,
        0.0,
        -0.0010960414074361324
      ],
      "type": "Gaussian"
    },
    {
      "fit": [
        -0.9936480522155762,
        0.0,
        0.993896484375
      ],
      "groups": [],
      "impact_r": 0.003198942169547081,
      "name": "CMS_tauFR_p0_dm10_E_2018_13TeV",
      "prefit": [
        -1.0,
        0.0,
        1.0
      ],
      "r": [
        -0.003198942169547081,
        0.0,
        0.0019948931876569986
      ],
      "type": "Gaussian"
    },
    {
      "fit": [
        -0.9935190677642822,
        0.0,
        0.9943949580192566
      ],
      "groups": [],
      "impact_r": 0.002443355042487383,
      "name": "CMS_tauFR_p0_dm11_B_2018_13TeV",
      "prefit": [
        -1.0,
        0.0,
        1.0
      ],
      "r": [
        0.00153944524936378,
        0.0,
        -0.002443355042487383
      ],
      "type": "Gaussian"
    },
    {
      "fit": [
        -0.9935198426246643,
        0.0,
        0.9943017959594727
      ],
      "groups": [],
      "impact_r": 0.0009504617191851139,
      "name": "CMS_tauFR_p0_dm11_E_2018_13TeV",
      "prefit": [
        -1.0,
        0.0,
        1.0
      ],
      "r": [
        -0.0007921661017462611,
        0.0,
        0.0009504617191851139
      ],
      "type": "Gaussian"
    },
    {
      "fit": [
        -0.9941314458847046,
        0.0,
        0.9930843710899353
      ],
      "groups": [],
      "impact_r": 0.0038083873223513365,
      "name": "CMS_tauFR_p0_dm1_B_2018_13TeV",
      "prefit": [
        -1.0,
        0.0,
        1.0
      ],
      "r": [
        0.003398675937205553,
        0.0,
        -0.0038083873223513365
      ],
      "type": "Gaussian"
    },
    {
      "fit": [
        -0.9938750863075256,
        0.0,
        0.9940655827522278
      ],
      "groups": [],
      "impact_r": 0.00037346495082601905,
      "name": "CMS_tauFR_p0_dm1_E_2018_13TeV",
      "prefit": [
        -1.0,
        0.0,
        1.0
      ],
      "r": [
        -0.00025728801847435534,
        0.0,
        0.00037346495082601905
      ],
      "type": "Gaussian"
    },
    {
      "fit": [
        -0.9936252236366272,
        0.0,
        0.9940676689147949
      ],
      "groups": [],
      "impact_r": 0.0036958949640393257,
      "name": "CMS_tauFR_p1_dm0_B_2018_13TeV",
      "prefit": [
        -1.0,
        0.0,
        1.0
      ],
      "r": [
        0.0015731557505205274,
        0.0,
        -0.0036958949640393257
      ],
      "type": "Gaussian"
    },
    {
      "fit": [
        -0.9937297105789185,
        0.0,
        0.9937856793403625
      ],
      "groups": [],
      "impact_r": 0.0010963883250951767,
      "name": "CMS_tauFR_p1_dm0_E_2018_13TeV",
      "prefit": [
        -1.0,
        0.0,
        1.0
      ],
      "r": [
        -0.0010963883250951767,
        0.0,
        0.0004316616104915738
      ],
      "type": "Gaussian"
    },
    {
      "fit": [
        -0.9937424659729004,
        0.0,
        0.9941328167915344
      ],
      "groups": [],
      "impact_r": 0.0013642831472679973,
      "name": "CMS_tauFR_p1_dm10_B_2018_13TeV",
      "prefit": [
        -1.0,
        0.0,
        1.0
      ],
      "r": [
        0.0013642831472679973,
        0.0,
        -0.0010334725957363844
      ],
      "type": "Gaussian"
    },
    {
      "fit": [
        -0.9937223792076111,
        0.0,
        0.9937880635261536
      ],
      "groups": [],
      "impact_r": 0.0023477370850741863,
      "name": "CMS_tauFR_p1_dm10_E_2018_13TeV",
      "prefit": [
        -1.0,
        0.0,
        1.0
      ],
      "r": [
        -0.0023477370850741863,
        0.0,
        0.00011348533007549122
      ],
      "type": "Gaussian"
    },
    {
      "fit": [
        -0.9933873414993286,
        0.0,
        0.9943177700042725
      ],
      "groups": [],
      "impact_r": 0.0021125709172338247,
      "name": "CMS_tauFR_p1_dm11_B_2018_13TeV",
      "prefit": [
        -1.0,
        0.0,
        1.0
      ],
      "r": [
        0.0013496056199073792,
        0.0,
        -0.0021125709172338247
      ],
      "type": "Gaussian"
    },
    {
      "fit": [
        -0.9934989809989929,
        0.0,
        0.9942686557769775
      ],
      "groups": [],
      "impact_r": 0.00028872647089883685,
      "name": "CMS_tauFR_p1_dm11_E_2018_13TeV",
      "prefit": [
        -1.0,
        0.0,
        1.0
      ],
      "r": [
        -0.00016300499555654824,
        0.0,
        0.00028872647089883685
      ],
      "type": "Gaussian"
    },
    {
      "fit": [
        -0.9941172003746033,
        0.0,
        0.9939503073692322
      ],
      "groups": [],
      "impact_r": 0.003238123143091798,
      "name": "CMS_tauFR_p1_dm1_B_2018_13TeV",
      "prefit": [
        -1.0,
        0.0,
        1.0
      ],
      "r": [
        0.0026504299603402615,
        0.0,
        -0.003238123143091798
      ],
      "type": "Gaussian"
    },
    {
      "fit": [
        -0.9938549995422363,
        0.0,
        0.9938067197799683
      ],
      "groups": [],
      "impact_r": 0.00036640404141508043,
      "name": "CMS_tauFR_p1_dm1_E_2018_13TeV",
      "prefit": [
        -1.0,
        0.0,
        1.0
      ],
      "r": [
        0.00036640404141508043,
        0.0,
        -0.0001783499465091154
      ],
      "type": "Gaussian"
    },
    {
      "fit": [
        -0.9919306039810181,
        0.0,
        0.9920995831489563
      ],
      "groups": [],
      "impact_r": 0.0009628401603549719,
      "name": "CMS_tau_tracking_pizero_13TeV",
      "prefit": [
        -1.0,
        0.0,
        1.0
      ],
      "r": [
        -0.0009628401603549719,
        0.0,
        0.0007150748861022294
      ],
      "type": "Gaussian"
    },
    {
      "fit": [
        -0.9873791933059692,
        0.0,
        0.9873118996620178
      ],
      "groups": [],
      "impact_r": 0.0015930529916658998,
      "name": "CMS_tau_tracking_pizero_2018_13TeV",
      "prefit": [
        -1.0,
        0.0,
        1.0
      ],
      "r": [
        -0.0015930529916658998,
        0.0,
        0.001370724174194038
      ],
      "type": "Gaussian"
    },
    {
      "fit": [
        -0.9936274290084839,
        0.0,
        0.988396942615509
      ],
      "groups": [],
      "impact_r": 0.0010586774442344904,
      "name": "CMS_tau_tracking_prong_13TeV",
      "prefit": [
        -1.0,
        0.0,
        1.0
      ],
      "r": [
        0.00044011452700942755,
        0.0,
        0.0010586774442344904
      ],
      "type": "Gaussian"
    },
    {
      "fit": [
        -0.9940264225006104,
        0.0,
        0.9767048358917236
      ],
      "groups": [],
      "impact_r": 0.0022790408693253994,
      "name": "CMS_tau_tracking_prong_2018_13TeV",
      "prefit": [
        -1.0,
        0.0,
        1.0
      ],
      "r": [
        0.0022790408693253994,
        0.0,
        0.0020581905264407396
      ],
      "type": "Gaussian"
    },
    {
      "fit": [
        -0.9590848088264465,
        0.0,
        0.9578589797019958
      ],
      "groups": [],
      "impact_r": 0.003686329582706094,
      "name": "CMS_tauid_pt30to35_2018_13TeV",
      "prefit": [
        -1.0,
        0.0,
        1.0
      ],
      "r": [
        -0.003686329582706094,
        0.0,
        0.0035195795353502035
      ],
      "type": "Gaussian"
    },
    {
      "fit": [
        -0.9794586300849915,
        0.0,
        0.9796540141105652
      ],
      "groups": [],
      "impact_r": 0.0021848028991371393,
      "name": "CMS_tauid_pt35to40_2018_13TeV",
      "prefit": [
        -1.0,
        0.0,
        1.0
      ],
      "r": [
        -0.0021848028991371393,
        0.0,
        0.0019182340474799275
      ],
      "type": "Gaussian"
    },
    {
      "fit": [
        -0.9592574238777161,
        0.0,
        0.9703561663627625
      ],
      "groups": [],
      "impact_r": 0.0049732462503015995,
      "name": "CMS_tauid_ptgt40_2018_13TeV",
      "prefit": [
        -1.0,
        0.0,
        1.0
      ],
      "r": [
        0.0049732462503015995,
        0.0,
        -0.003316414775326848
      ],
      "type": "Gaussian"
    },
    {
      "fit": [
        -0.9939141869544983,
        0.0,
        0.9943090677261353
      ],
      "groups": [],
      "impact_r": 0.0004893370787613094,
      "name": "QCDscale_ggH",
      "prefit": [
        -0.9999999999999999,
        0.0,
        0.9999999999999999
      ],
      "r": [
        0.000447526341304183,
        0.0,
        -0.0004893370787613094
      ],
      "type": "Gaussian"
    },
    {
      "fit": [
        -0.9938669800758362,
        0.0,
        0.9943556189537048
      ],
      "groups": [],
      "impact_r": 0.0,
      "name": "QCDscale_qqH",
      "prefit": [
        -0.9999999999999999,
        0.0,
        0.9999999999999999
      ],
      "r": [
        0.0,
        0.0,
        0.0
      ],
      "type": "Gaussian"
    },
    {
      "fit": [
        -0.9938670992851257,
        0.0,
        0.9943554997444153
      ],
      "groups": [],
      "impact_r": 6.693544037261745e-06,
      "name": "acceptance_pdf_gg",
      "prefit": [
        -0.9999999999999999,
        0.0,
        0.9999999999999999
      ],
      "r": [
        -6.693544037261745e-06,
        0.0,
        4.684868599724723e-06
      ],
      "type": "Gaussian"
    },
    {
      "fit": [
        -0.9938669800758362,
        0.0,
        0.9943556189537048
      ],
      "groups": [],
      "impact_r": 0.0,
      "name": "acceptance_pdf_vbf",
      "prefit": [
        -0.9999999999999999,
        0.0,
        0.9999999999999999
      ],
      "r": [
        0.0,
        0.0,
        0.0
      ],
      "type": "Gaussian"
    },
    {
      "fit": [
        -0.9938852190971375,
        0.0,
        0.9943388104438782
      ],
      "groups": [],
      "impact_r": 0.000135412672534585,
      "name": "acceptance_scale_gg",
      "prefit": [
        -0.9999999999999999,
        0.0,
        0.9999999999999999
      ],
      "r": [
        0.00012229244748596102,
        0.0,
        -0.000135412672534585
      ],
      "type": "Gaussian"
    },
    {
      "fit": [
        -0.9938669800758362,
        0.0,
        0.9943556189537048
      ],
      "groups": [],
      "impact_r": 0.0,
      "name": "acceptance_scale_vbf",
      "prefit": [
        -0.9999999999999999,
        0.0,
        0.9999999999999999
      ],
      "r": [
        0.0,
        0.0,
        0.0
      ],
      "type": "Gaussian"
    },
    {
      "fit": [
        -0.993651270866394,
        0.0,
        0.9934593439102173
      ],
      "groups": [],
      "impact_r": 0.0015419668052345514,
      "name": "norm_Diboson",
      "prefit": [
        -0.9999999999999999,
        0.0,
        0.9999999999999999
      ],
      "r": [
        0.0007008203538134694,
        0.0,
        -0.0015419668052345514
      ],
      "type": "Gaussian"
    },
    {
      "fit": [
        -0.9936555027961731,
        0.0,
        0.9934594631195068
      ],
      "groups": [],
      "impact_r": 0.0009102554759010673,
      "name": "norm_Diboson_mutauh_0jet",
      "prefit": [
        -0.9999999999999999,
        0.0,
        0.9999999999999999
      ],
      "r": [
        0.0007365989731624722,
        0.0,
        -0.0009102554759010673
      ],
      "type": "Gaussian"
    },
    {
      "fit": [
        -0.9938890933990479,
        0.0,
        0.9943283796310425
      ],
      "groups": [],
      "impact_r": 9.892618982121348e-05,
      "name": "norm_EWK",
      "prefit": [
        -0.9999999999999999,
        0.0,
        0.9999999999999999
      ],
      "r": [
        8.05385279818438e-05,
        0.0,
        -9.892618982121348e-05
      ],
      "type": "Gaussian"
    },
    {
      "fit": [
        -0.993874192237854,
        0.0,
        0.9943479299545288
      ],
      "groups": [],
      "impact_r": 4.9644222599454224e-05,
      "name": "norm_EWK_mutauh_0jet",
      "prefit": [
        -0.9999999999999999,
        0.0,
        0.9999999999999999
      ],
      "r": [
        3.957840090151876e-05,
        0.0,
        -4.9644222599454224e-05
      ],
      "type": "Gaussian"
    },
    {
      "fit": [
        -0.3498859107494354,
        0.0,
        0.349838525056839
      ],
      "groups": [],
      "impact_r": 0.016989918425679207,
      "name": "norm_Fakes",
      "prefit": [
        -0.9999999999999999,
        0.0,
        0.9999999999999999
      ],
      "r": [
        0.016989918425679207,
        0.0,
        -0.016912657767534256
      ],
      "type": "Gaussian"
    },
    {
      "fit": [
        -0.9349813461303711,
        0.0,
        0.9351930022239685
      ],
      "groups": [],
      "impact_r": 0.0023204947356134653,
      "name": "norm_Fakes_mutauh_0jet",
      "prefit": [
        -0.9999999999999999,
        0.0,
        0.9999999999999999
      ],
      "r": [
        0.0020734546706080437,
        0.0,
        -0.0023204947356134653
      ],
      "type": "Gaussian"
    },
    {
      "fit": [
        -0.9938988089561462,
        0.0,
        0.994319498538971
      ],
      "groups": [],
      "impact_r": 9.561316255712882e-05,
      "name": "norm_T",
      "prefit": [
        -0.9999999999999999,
        0.0,
        0.9999999999999999
      ],
      "r": [
        8.300197077915072e-05,
        0.0,
        -9.561316255712882e-05
      ],
      "type": "Gaussian"
    },
    {
      "fit": [
        -0.9940396547317505,
        0.0,
        0.9941427111625671
      ],
      "groups": [],
      "impact_r": 0.0009682305390015244,
      "name": "norm_TT",
      "prefit": [
        -0.9999999999999999,
        0.0,
        0.9999999999999999
      ],
      "r": [
        -0.000879721250385046,
        0.0,
        0.0009682305390015244
      ],
      "type": "Gaussian"
    },
    {
      "fit": [
        -0.993976891040802,
        0.0,
        0.9942229390144348
      ],
      "groups": [],
      "impact_r": 0.0008054827339947224,
      "name": "norm_TT_mutauh_0jet",
      "prefit": [
        -0.9999999999999999,
        0.0,
        0.9999999999999999
      ],
      "r": [
        -0.00034465541830286384,
        0.0,
        0.0008054827339947224
      ],
      "type": "Gaussian"
    },
    {
      "fit": [
        -0.9938988089561462,
        0.0,
        0.994319498538971
      ],
      "groups": [],
      "impact_r": 9.561357001075521e-05,
      "name": "norm_T_mutauh_0jet",
      "prefit": [
        -0.9999999999999999,
        0.0,
        0.9999999999999999
      ],
      "r": [
        8.299102046294138e-05,
        0.0,
        -9.561357001075521e-05
      ],
      "type": "Gaussian"
    },
    {
      "fit": [
        -0.9748329520225525,
        0.0,
        0.9745242595672607
      ],
      "groups": [],
      "impact_r": 0.01564144343137741,
      "name": "norm_Zothers",
      "prefit": [
        -0.9999999999999999,
        0.0,
        0.9999999999999999
      ],
      "r": [
        -0.015607851557433605,
        0.0,
        0.01564144343137741
      ],
      "type": "Gaussian"
    },
    {
      "fit": [
        -0.9651314616203308,
        0.0,
        0.9634817838668823
      ],
      "groups": [],
      "impact_r": 0.019877713173627853,
      "name": "norm_Zothers_mutauh_0jet",
      "prefit": [
        -0.9999999999999999,
        0.0,
        0.9999999999999999
      ],
      "r": [
        -0.019877713173627853,
        0.0,
        0.019758785143494606
      ],
      "type": "Gaussian"
    },
    {
      "fit": [
        -0.9939008951187134,
        0.0,
        0.9943227767944336
      ],
      "groups": [],
      "impact_r": 0.0001724686153465882,
      "name": "pdf_Higgs_gg",
      "prefit": [
        -0.9999999999999999,
        0.0,
        0.9999999999999999
      ],
      "r": [
        0.00015880468708928674,
        0.0,
        -0.0001724686153465882
      ],
      "type": "Gaussian"
    },
    {
      "fit": [
        -0.9938669800758362,
        0.0,
        0.9943556189537048
      ],
      "groups": [],
      "impact_r": 1.773282292560907e-06,
      "name": "pdf_Higgs_qq",
      "prefit": [
        -0.9999999999999999,
        0.0,
        0.9999999999999999
      ],
      "r": [
        -1.0157638996588503e-07,
        0.0,
        -1.773282292560907e-06
      ],
      "type": "Gaussian"
    },
    {
      "fit": [
        -0.8673363924026489,
        0.0,
        0.8697519898414612
      ],
      "groups": [],
      "impact_r": 0.02008555270731449,
      "name": "prop_binHMuTau_mutauhad_1_2018_bin1",
      "prefit": [
        -0.9999999999999999,
        0.0,
        0.9999999999999999
      ],
      "r": [
        -0.02008555270731449,
        0.0,
        0.019904974848031998
      ],
      "type": "Gaussian"
    },
    {
      "fit": [
        -0.7667446136474609,
        0.0,
        0.7640396952629089
      ],
      "groups": [],
      "impact_r": 0.012662183493375778,
      "name": "prop_binHMuTau_mutauhad_1_2018_bin10",
      "prefit": [
        -0.9999999999999999,
        0.0,
        0.9999999999999999
      ],
      "r": [
        -0.01231536827981472,
        0.0,
        0.012662183493375778
      ],
      "type": "Gaussian"
    },
    {
      "fit": [
        -0.7570849061012268,
        0.0,
        0.7515971660614014
      ],
      "groups": [],
      "impact_r": 0.0092051075771451,
      "name": "prop_binHMuTau_mutauhad_1_2018_bin11",
      "prefit": [
        -0.9999999999999999,
        0.0,
        0.9999999999999999
      ],
      "r": [
        -0.0092051075771451,
        0.0,
        0.007400965318083763
      ],
      "type": "Gaussian"
    },
    {
      "fit": [
        -0.7671283483505249,
        0.0,
        0.7569431066513062
      ],
      "groups": [],
      "impact_r": 0.020861469209194183,
      "name": "prop_binHMuTau_mutauhad_1_2018_bin12",
      "prefit": [
        -0.9999999999999999,
        0.0,
        0.9999999999999999
      ],
      "r": [
        -0.020861469209194183,
        0.0,
        0.014625531621277332
      ],
      "type": "Gaussian"
    },
    {
      "fit": [
        -0.7680774927139282,
        0.0,
        0.7707037925720215
      ],
      "groups": [],
      "impact_r": 0.027222083881497383,
      "name": "prop_binHMuTau_mutauhad_1_2018_bin13",
      "prefit": [
        -0.9999999999999999,
        0.0,
        0.9999999999999999
      ],
      "r": [
        -0.027222083881497383,
        0.0,
        0.02498847432434559
      ],
      "type": "Gaussian"
    },
    {
      "fit": [
        -0.8080931305885315,
        0.0,
        0.8145008683204651
      ],
      "groups": [],
      "impact_r": 0.01964169554412365,
      "name": "prop_binHMuTau_mutauhad_1_2018_bin14",
      "prefit": [
        -0.9999999999999999,
        0.0,
        0.9999999999999999
      ],
      "r": [
        -0.01964169554412365,
        0.0,
        0.018963836133480072
      ],
      "type": "Gaussian"
    },
    {
      "fit": [
        -0.8582600355148315,
        0.0,
        0.8582613468170166
      ],
      "groups": [],
      "impact_r": 0.021338757127523422,
      "name": "prop_binHMuTau_mutauhad_1_2018_bin15",
      "prefit": [
        -0.9999999999999999,
        0.0,
        0.9999999999999999
      ],
      "r": [
        0.02007393166422844,
        0.0,
        -0.021338757127523422
      ],
      "type": "Gaussian"
    },
    {
      "fit": [
        -0.9588021636009216,
        0.0,
        0.9585558176040649
      ],
      "groups": [],
      "impact_r": 0.08768419176340103,
      "name": "prop_binHMuTau_mutauhad_1_2018_bin16",
      "prefit": [
        -0.9999999999999999,
        0.0,
        0.9999999999999999
      ],
      "r": [
        0.08687153458595276,
        0.0,
        -0.08768419176340103
      ],
      "type": "Gaussian"
    },
    {
      "fit": [
        -0.8468733429908752,
        0.0,
        0.8485934734344482
      ],
      "groups": [],
      "impact_r": 0.009284901432693005,
      "name": "prop_binHMuTau_mutauhad_1_2018_bin2",
      "prefit": [
        -0.9999999999999999,
        0.0,
        0.9999999999999999
      ],
      "r": [
        -0.008798361755907536,
        0.0,
        0.009284901432693005
      ],
      "type": "Gaussian"
    },
    {
      "fit": [
        -0.8332855105400085,
        0.0,
        0.8339122533798218
      ],
      "groups": [],
      "impact_r": 0.0019746969919651747,
      "name": "prop_binHMuTau_mutauhad_1_2018_bin3",
      "prefit": [
        -0.9999999999999999,
        0.0,
        0.9999999999999999
      ],
      "r": [
        0.0019746969919651747,
        0.0,
        -0.001457652193494141
      ],
      "type": "Gaussian"
    },
    {
      "fit": [
        -0.8512775301933289,
        0.0,
        0.8517124056816101
      ],
      "groups": [],
      "impact_r": 0.009962818585336208,
      "name": "prop_binHMuTau_mutauhad_1_2018_bin4",
      "prefit": [
        -0.9999999999999999,
        0.0,
        0.9999999999999999
      ],
      "r": [
        0.009962818585336208,
        0.0,
        -0.009264887310564518
      ],
      "type": "Gaussian"
    },
    {
      "fit": [
        -0.8562606573104858,
        0.0,
        0.8565540313720703
      ],
      "groups": [],
      "impact_r": 0.012513142079114914,
      "name": "prop_binHMuTau_mutauhad_1_2018_bin5",
      "prefit": [
        -0.9999999999999999,
        0.0,
        0.9999999999999999
      ],
      "r": [
        0.012513142079114914,
        0.0,
        -0.011509770527482033
      ],
      "type": "Gaussian"
    },
    {
      "fit": [
        -0.8471274971961975,
        0.0,
        0.8466646075248718
      ],
      "groups": [],
      "impact_r": 0.004096608608961105,
      "name": "prop_binHMuTau_mutauhad_1_2018_bin6",
      "prefit": [
        -0.9999999999999999,
        0.0,
        0.9999999999999999
      ],
      "r": [
        0.004096608608961105,
        0.0,
        -0.0033974514808505774
      ],
      "type": "Gaussian"
    },
    {
      "fit": [
        -0.8094453811645508,
        0.0,
        0.8108751773834229
      ],
      "groups": [],
      "impact_r": 0.01835128851234913,
      "name": "prop_binHMuTau_mutauhad_1_2018_bin8",
      "prefit": [
        -0.9999999999999999,
        0.0,
        0.9999999999999999
      ],
      "r": [
        -0.01764129288494587,
        0.0,
        0.01835128851234913
      ],
      "type": "Gaussian"
    },
    {
      "fit": [
        -0.7879213690757751,
        0.0,
        0.8158842325210571
      ],
      "groups": [],
      "impact_r": 0.011594732291996479,
      "name": "prop_binHMuTau_mutauhad_1_2018_bin9",
      "prefit": [
        -0.9999999999999999,
        0.0,
        0.9999999999999999
      ],
      "r": [
        -0.011594732291996479,
        0.0,
        0.005775476805865765
      ],
      "type": "Gaussian"
    }
  ]
}