{
  "POIs": [
    {
      "fit": [
        -0.7755855917930603,
        2.7906121857768085e-09,
        0.8025193214416504
      ],
      "name": "r"
    }
  ],
  "method": "default",
  "params": [
    {
      "fit": [
        -0.9938670992851257,
        0.0,
        0.9943554997444153
      ],
      "groups": [],
      "impact_r": 0.0001064011812559329,
      "name": "BR_htt_PU_alphas",
      "prefit": [
        -0.9999999999999999,
        0.0,
        0.9999999999999999
      ],
      "r": [
        0.00010577513603493571,
        0.0,
        -0.0001064011812559329
      ],
      "type": "Gaussian"
    },
    {
      "fit": [
        -0.9938673377037048,
        0.0,
        0.9943552613258362
      ],
      "groups": [],
      "impact_r": 0.0001698806299827993,
      "name": "BR_htt_PU_mq",
      "prefit": [
        -0.9999999999999999,
        0.0,
        0.9999999999999999
      ],
      "r": [
        0.00016829701780807227,
        0.0,
        -0.0001698806299827993
      ],
      "type": "Gaussian"
    },
    {
      "fit": [
        -0.9938680529594421,
        0.0,
        0.9943545460700989
      ],
      "groups": [],
      "impact_r": 0.0002916281810030341,
      "name": "BR_htt_THU",
      "prefit": [
        -0.9999999999999999,
        0.0,
        0.9999999999999999
      ],
      "r": [
        0.00028704956639558077,
        0.0,
        -0.0002916281810030341
      ],
      "type": "Gaussian"
    },
    {
      "fit": [
        -0.9607523679733276,
        0.0,
        0.9466989040374756
      ],
      "groups": [],
      "impact_r": 0.048709917813539505,
      "name": "CMS_EES_13TeV",
      "prefit": [
        -1.0,
        0.0,
        1.0
      ],
      "r": [
        -0.048709917813539505,
        0.0,
        0.013054038397967815
      ],
      "type": "Gaussian"
    },
    {
      "fit": [
        -0.9940868020057678,
        0.0,
        0.9943844676017761
      ],
      "groups": [],
      "impact_r": 1.219223122461699e-08,
      "name": "CMS_Jes_JetAbsoluteFlavMap_13TeV",
      "prefit": [
        -1.0,
        0.0,
        1.0
      ],
      "r": [
        1.4982843410393798e-08,
        2.7906121857768085e-09,
        1.3734961612499319e-08
      ],
      "type": "Gaussian"
    },
    {
      "fit": [
        -0.9805028438568115,
        -1.8845558003022234e-08,
        0.9820226430892944
      ],
      "groups": [],
      "impact_r": 0.03142326717129418,
      "name": "CMS_Jes_JetAbsoluteMPFBias_13TeV",
      "prefit": [
        -1.0,
        0.0,
        1.0
      ],
      "r": [
        0.03142327070236206,
        3.531067882533989e-09,
        0.002256526378914714
      ],
      "type": "Gaussian"
    },
    {
      "fit": [
        -0.9817276000976562,
        0.0,
        0.9843283891677856
      ],
      "groups": [],
      "impact_r": 0.022043542936444283,
      "name": "CMS_Jes_JetAbsoluteScale_13TeV",
      "prefit": [
        -1.0,
        0.0,
        1.0
      ],
      "r": [
        0.013896475546061993,
        0.0,
        -0.022043542936444283
      ],
      "type": "Gaussian"
    },
    {
      "fit": [
        -0.9734619855880737,
        8.677799812062403e-09,
        0.9814063310623169
      ],
      "groups": [],
      "impact_r": 0.056674243170428795,
      "name": "CMS_Jes_JetAbsoluteStat_13TeV",
      "prefit": [
        -1.0,
        0.0,
        1.0
      ],
      "r": [
        0.05667424574494362,
        2.574514823550089e-09,
        -0.008987155742943287
      ],
      "type": "Gaussian"
    },
    {
      "fit": [
        -0.9043588042259216,
        0.0,
        0.8697632551193237
      ],
      "groups": [],
      "impact_r": 0.15559861063957214,
      "name": "CMS_Jes_JetFlavorQCD_13TeV",
      "prefit": [
        -1.0,
        0.0,
        1.0
      ],
      "r": [
        0.08228693157434464,
        0.0,
        0.15559861063957214
      ],
      "type": "Gaussian"
    },
    {
      "fit": [
        -0.9679429531097412,
        0.0,
        0.9742059707641602
      ],
      "groups": [],
      "impact_r": 0.05615178868174553,
      "name": "CMS_Jes_JetFragmentation_13TeV",
      "prefit": [
        -1.0,
        0.0,
        1.0
      ],
      "r": [
        0.05615178868174553,
        0.0,
        0.022521784529089928
      ],
      "type": "Gaussian"
    },
    {
      "fit": [
        -0.9119240641593933,
        0.0,
        0.9590209126472473
      ],
      "groups": [],
      "impact_r": 0.05930589139461517,
      "name": "CMS_Jes_JetPileUpDataMC_13TeV",
      "prefit": [
        -1.0,
        0.0,
        1.0
      ],
      "r": [
        0.05930589139461517,
        0.0,
        0.04702254757285118
      ],
      "type": "Gaussian"
    },
    {
      "fit": [
        -0.9561263918876648,
        0.0,
        0.9508742690086365
      ],
      "groups": [],
      "impact_r": 0.04935268312692642,
      "name": "CMS_Jes_JetPileUpPtBB_13TeV",
      "prefit": [
        -1.0,
        0.0,
        1.0
      ],
      "r": [
        0.04935268312692642,
        0.0,
        0.02858210727572441
      ],
      "type": "Gaussian"
    },
    {
      "fit": [
        -0.6781778335571289,
        0.0,
        0.9619234204292297
      ],
      "groups": [],
      "impact_r": 0.08744793385267258,
      "name": "CMS_Jes_JetPileUpPtEC1_13TeV",
      "prefit": [
        -1.0,
        0.0,
        1.0
      ],
      "r": [
        0.0326751247048378,
        0.0,
        0.08744793385267258
      ],
      "type": "Gaussian"
    },
    {
      "fit": [
        -0.9401585459709167,
        0.0,
        0.9426589608192444
      ],
      "groups": [],
      "impact_r": 0.12569725513458252,
      "name": "CMS_Jes_JetPileUpPtEC2_13TeV",
      "prefit": [
        -1.0,
        0.0,
        1.0
      ],
      "r": [
        0.12569725513458252,
        0.0,
        0.11235099285840988
      ],
      "type": "Gaussian"
    },
    {
      "fit": [
        -0.9750930666923523,
        0.0,
        0.9535949230194092
      ],
      "groups": [],
      "impact_r": 0.12784141302108765,
      "name": "CMS_Jes_JetPileUpPtHF_13TeV",
      "prefit": [
        -1.0,
        0.0,
        1.0
      ],
      "r": [
        -0.02592810057103634,
        0.0,
        0.12784141302108765
      ],
      "type": "Gaussian"
    },
    {
      "fit": [
        -0.9754582643508911,
        -3.03165919035564e-08,
        0.9525678753852844
      ],
      "groups": [],
      "impact_r": 0.16582405304010628,
      "name": "CMS_Jes_JetPileUpPtRef_13TeV",
      "prefit": [
        -1.0,
        0.0,
        1.0
      ],
      "r": [
        0.10018675029277802,
        2.6315856160863405e-09,
        0.1658240556716919
      ],
      "type": "Gaussian"
    },
    {
      "fit": [
        -0.8283016681671143,
        -3.387455294046049e-08,
        0.8833428621292114
      ],
      "groups": [],
      "impact_r": 0.2405477289375053,
      "name": "CMS_Jes_JetRelativeBal_13TeV",
      "prefit": [
        -1.0,
        0.0,
        1.0
      ],
      "r": [
        0.07111168652772903,
        2.5812401105440586e-09,
        0.24054773151874542
      ],
      "type": "Gaussian"
    },
    {
      "fit": [
        -0.9735733270645142,
        0.0,
        0.9593851566314697
      ],
      "groups": [],
      "impact_r": 0.08254709094762802,
      "name": "CMS_Jes_JetRelativeFSR_13TeV",
      "prefit": [
        -1.0,
        0.0,
        1.0
      ],
      "r": [
        0.06198469549417496,
        0.0,
        0.08254709094762802
      ],
      "type": "Gaussian"
    },
    {
      "fit": [
        -0.9914559125900269,
        0.0,
        0.9926970601081848
      ],
      "groups": [],
      "impact_r": 0.0050697592087090015,
      "name": "CMS_Jes_JetRelativeJEREC1_13TeV",
      "prefit": [
        -1.0,
        0.0,
        1.0
      ],
      "r": [
        0.0006443879101425409,
        0.0,
        0.0050697592087090015
      ],
      "type": "Gaussian"
    },
    {
      "fit": [
        -0.9928175806999207,
        0.0,
        0.9874458312988281
      ],
      "groups": [],
      "impact_r": 0.028293708339333534,
      "name": "CMS_Jes_JetRelativeJEREC2_13TeV",
      "prefit": [
        -1.0,
        0.0,
        1.0
      ],
      "r": [
        0.00017643206228967756,
        0.0,
        0.028293708339333534
      ],
      "type": "Gaussian"
    },
    {
      "fit": [
        -0.9941732287406921,
        0.0,
        0.9938786625862122
      ],
      "groups": [],
      "impact_r": 0.009879855439066887,
      "name": "CMS_Jes_JetRelativeJERHF_13TeV",
      "prefit": [
        -1.0,
        0.0,
        1.0
      ],
      "r": [
        0.009879855439066887,
        0.0,
        -0.005673297680914402
      ],
      "type": "Gaussian"
    },
    {
      "fit": [
        -0.9643802046775818,
        0.0,
        0.9766791462898254
      ],
      "groups": [],
      "impact_r": 0.023828264325857162,
      "name": "CMS_Jes_JetRelativePtBB_13TeV",
      "prefit": [
        -1.0,
        0.0,
        1.0
      ],
      "r": [
        0.021257393062114716,
        0.0,
        0.023828264325857162
      ],
      "type": "Gaussian"
    },
    {
      "fit": [
        -0.6744351983070374,
        0.0,
        0.9533312320709229
      ],
      "groups": [],
      "impact_r": 0.10912581533193588,
      "name": "CMS_Jes_JetRelativePtEC1_13TeV",
      "prefit": [
        -1.0,
        0.0,
        1.0
      ],
      "r": [
        -0.024081623181700706,
        0.0,
        0.10912581533193588
      ],
      "type": "Gaussian"
    },
    {
      "fit": [
        -0.9348065853118896,
        -3.1937794631176075e-08,
        0.92561936378479
      ],
      "groups": [],
      "impact_r": 0.10267208971792385,
      "name": "CMS_Jes_JetRelativePtEC2_13TeV",
      "prefit": [
        -1.0,
        0.0,
        1.0
      ],
      "r": [
        0.10267209261655807,
        2.898634221537577e-09,
        0.06403876841068268
      ],
      "type": "Gaussian"
    },
    {
      "fit": [
        -0.9060986042022705,
        0.0,
        0.93768310546875
      ],
      "groups": [],
      "impact_r": 0.1768328696489334,
      "name": "CMS_Jes_JetRelativePtHF_13TeV",
      "prefit": [
        -1.0,
        0.0,
        1.0
      ],
      "r": [
        0.07256302982568741,
        0.0,
        0.1768328696489334
      ],
      "type": "Gaussian"
    },
    {
      "fit": [
        -0.9488679766654968,
        0.0,
        0.9649298191070557
      ],
      "groups": [],
      "impact_r": 0.03132002055644989,
      "name": "CMS_Jes_JetRelativeStatEC_13TeV",
      "prefit": [
        -1.0,
        0.0,
        1.0
      ],
      "r": [
        0.03132002055644989,
        0.0,
        0.018076816573739052
      ],
      "type": "Gaussian"
    },
    {
      "fit": [
        -0.984929084777832,
        0.0,
        0.9904467463493347
      ],
      "groups": [],
      "impact_r": 0.018639538437128067,
      "name": "CMS_Jes_JetRelativeStatFSR_13TeV",
      "prefit": [
        -1.0,
        0.0,
        1.0
      ],
      "r": [
        0.018639538437128067,
        0.0,
        0.0034377407282590866
      ],
      "type": "Gaussian"
    },
    {
      "fit": [
        -0.9606614112854004,
        0.0,
        0.9841630458831787
      ],
      "groups": [],
      "impact_r": 0.048931900411844254,
      "name": "CMS_Jes_JetRelativeStatHF_13TeV",
      "prefit": [
        -1.0,
        0.0,
        1.0
      ],
      "r": [
        0.048931900411844254,
        0.0,
        0.016809560358524323
      ],
      "type": "Gaussian"
    },
    {
      "fit": [
        -0.9820697903633118,
        0.0,
        0.9727924466133118
      ],
      "groups": [],
      "impact_r": 0.06401258707046509,
      "name": "CMS_Jes_JetSinglePionECAL_13TeV",
      "prefit": [
        -1.0,
        0.0,
        1.0
      ],
      "r": [
        0.03728485479950905,
        0.0,
        0.06401258707046509
      ],
      "type": "Gaussian"
    },
    {
      "fit": [
        -0.9772098660469055,
        5.764455579537753e-11,
        0.9735140800476074
      ],
      "groups": [],
      "impact_r": 0.06604678711490486,
      "name": "CMS_Jes_JetSinglePionHCAL_13TeV",
      "prefit": [
        -1.0,
        0.0,
        1.0
      ],
      "r": [
        0.020174795761704445,
        2.1736159538932043e-09,
        0.06604678928852081
      ],
      "type": "Gaussian"
    },
    {
      "fit": [
        -0.9709847569465637,
        7.335458462875977e-09,
        0.9831780195236206
      ],
      "groups": [],
      "impact_r": 0.06758038402014765,
      "name": "CMS_Jes_JetTimePtEta_13TeV",
      "prefit": [
        -1.0,
        0.0,
        1.0
      ],
      "r": [
        0.06758038699626923,
        2.976121571407475e-09,
        0.030445054173469543
      ],
      "type": "Gaussian"
    },
    {
      "fit": [
        -0.9699538350105286,
        -1.3255515796117834e-08,
        0.951714813709259
      ],
      "groups": [],
      "impact_r": 0.06432721484786796,
      "name": "CMS_MET_chargedUes_13TeV",
      "prefit": [
        -1.0,
        0.0,
        1.0
      ],
      "r": [
        0.06432721763849258,
        2.7906246202746843e-09,
        -0.015519010834395885
      ],
      "type": "Gaussian"
    },
    {
      "fit": [
        -0.8816753625869751,
        0.0,
        0.8284459710121155
      ],
      "groups": [],
      "impact_r": 0.1917610764503479,
      "name": "CMS_MET_hcalUes_13TeV",
      "prefit": [
        -1.0,
        0.0,
        1.0
      ],
      "r": [
        0.1917610764503479,
        0.0,
        -0.015120337717235088
      ],
      "type": "Gaussian"
    },
    {
      "fit": [
        -0.8826422095298767,
        0.0,
        0.8288730382919312
      ],
      "groups": [],
      "impact_r": 0.19294965267181396,
      "name": "CMS_MET_hfUes_13TeV",
      "prefit": [
        -1.0,
        0.0,
        1.0
      ],
      "r": [
        0.19294965267181396,
        0.0,
        0.09689200669527054
      ],
      "type": "Gaussian"
    },
    {
      "fit": [
        -0.9436827301979065,
        0.0,
        0.9489030241966248
      ],
      "groups": [],
      "impact_r": 0.027814289554953575,
      "name": "CMS_Pileup_13TeV",
      "prefit": [
        -1.0,
        0.0,
        1.0
      ],
      "r": [
        0.027814289554953575,
        0.0,
        -0.020427444949746132
      ],
      "type": "Gaussian"
    },
    {
      "fit": [
        -0.9935874938964844,
        0.0,
        0.994287371635437
      ],
      "groups": [],
      "impact_r": 0.004251924809068441,
      "name": "CMS_TauFakeRate_p0_dm0_B_13TeV",
      "prefit": [
        -1.0,
        0.0,
        1.0
      ],
      "r": [
        0.00419622240588069,
        0.0,
        -0.004251924809068441
      ],
      "type": "Gaussian"
    },
    {
      "fit": [
        -0.993632435798645,
        3.659628688978955e-08,
        0.9942978620529175
      ],
      "groups": [],
      "impact_r": 0.0028467739633564193,
      "name": "CMS_TauFakeRate_p0_dm0_E_13TeV",
      "prefit": [
        -1.0,
        0.0,
        1.0
      ],
      "r": [
        -0.00284678116440773,
        -7.2010513108011764e-09,
        0.0022147134877741337
      ],
      "type": "Gaussian"
    },
    {
      "fit": [
        -0.9938395619392395,
        0.0,
        0.9940426349639893
      ],
      "groups": [],
      "impact_r": 0.001408204436302185,
      "name": "CMS_TauFakeRate_p0_dm10_B_13TeV",
      "prefit": [
        -1.0,
        0.0,
        1.0
      ],
      "r": [
        0.001398967462591827,
        0.0,
        -0.001408204436302185
      ],
      "type": "Gaussian"
    },
    {
      "fit": [
        -0.9939484596252441,
        0.0,
        0.9939283132553101
      ],
      "groups": [],
      "impact_r": 0.001351270591840148,
      "name": "CMS_TauFakeRate_p0_dm10_E_13TeV",
      "prefit": [
        -1.0,
        0.0,
        1.0
      ],
      "r": [
        -0.0013377068098634481,
        0.0,
        0.001351270591840148
      ],
      "type": "Gaussian"
    },
    {
      "fit": [
        -0.9939693212509155,
        -2.37111201784046e-08,
        0.9939159154891968
      ],
      "groups": [],
      "impact_r": 0.012958919945234904,
      "name": "CMS_TauFakeRate_p0_dm1_B_13TeV",
      "prefit": [
        -1.0,
        0.0,
        1.0
      ],
      "r": [
        0.012958922423422337,
        2.478187433041512e-09,
        -0.012957031838595867
      ],
      "type": "Gaussian"
    },
    {
      "fit": [
        -0.9941131472587585,
        0.0,
        0.993768036365509
      ],
      "groups": [],
      "impact_r": 0.006970221176743507,
      "name": "CMS_TauFakeRate_p0_dm1_E_13TeV",
      "prefit": [
        -1.0,
        0.0,
        1.0
      ],
      "r": [
        -0.006864197552204132,
        0.0,
        0.006970221176743507
      ],
      "type": "Gaussian"
    },
    {
      "fit": [
        -0.9928654432296753,
        0.0,
        0.9932307600975037
      ],
      "groups": [],
      "impact_r": 0.026969287544488907,
      "name": "CMS_TauFakeRate_p1_dm0_B_13TeV",
      "prefit": [
        -1.0,
        0.0,
        1.0
      ],
      "r": [
        -0.026969287544488907,
        0.0,
        0.024590298533439636
      ],
      "type": "Gaussian"
    },
    {
      "fit": [
        -0.9921226501464844,
        4.706384615360548e-08,
        0.9924525618553162
      ],
      "groups": [],
      "impact_r": 0.0032773795443024056,
      "name": "CMS_TauFakeRate_p1_dm0_E_13TeV",
      "prefit": [
        -1.0,
        0.0,
        1.0
      ],
      "r": [
        0.0032673953101038933,
        3.2501663582706897e-09,
        -0.0032773762941360474
      ],
      "type": "Gaussian"
    },
    {
      "fit": [
        -0.9921287894248962,
        5.049892237707354e-08,
        0.9926325678825378
      ],
      "groups": [],
      "impact_r": 0.024031855995913176,
      "name": "CMS_TauFakeRate_p1_dm10_B_13TeV",
      "prefit": [
        -1.0,
        0.0,
        1.0
      ],
      "r": [
        -0.024031853303313255,
        2.6925999208060603e-09,
        0.023121004924178123
      ],
      "type": "Gaussian"
    },
    {
      "fit": [
        -0.9914082884788513,
        0.0,
        0.991461455821991
      ],
      "groups": [],
      "impact_r": 0.0034133433364331722,
      "name": "CMS_TauFakeRate_p1_dm10_E_13TeV",
      "prefit": [
        -1.0,
        0.0,
        1.0
      ],
      "r": [
        -0.0034133433364331722,
        0.0,
        0.003338192356750369
      ],
      "type": "Gaussian"
    },
    {
      "fit": [
        -0.9922062158584595,
        0.0,
        0.9919586181640625
      ],
      "groups": [],
      "impact_r": 0.05612224340438843,
      "name": "CMS_TauFakeRate_p1_dm1_B_13TeV",
      "prefit": [
        -1.0,
        0.0,
        1.0
      ],
      "r": [
        -0.05612224340438843,
        0.0,
        0.054696083068847656
      ],
      "type": "Gaussian"
    },
    {
      "fit": [
        -0.9893996119499207,
        4.394714636646313e-08,
        0.9897870421409607
      ],
      "groups": [],
      "impact_r": 0.01017192567452696,
      "name": "CMS_TauFakeRate_p1_dm1_E_13TeV",
      "prefit": [
        -1.0,
        0.0,
        1.0
      ],
      "r": [
        0.010171928443014622,
        2.7684876613420784e-09,
        -0.009510231204330921
      ],
      "type": "Gaussian"
    },
    {
      "fit": [
        -0.9745445847511292,
        0.0,
        0.9746937155723572
      ],
      "groups": [],
      "impact_r": 0.01967206783592701,
      "name": "CMS_eff_e",
      "prefit": [
        -0.9999999999999999,
        0.0,
        0.9999999999999999
      ],
      "r": [
        0.01967206783592701,
        0.0,
        -0.019086679443717003
      ],
      "type": "Gaussian"
    },
    {
      "fit": [
        -0.8927267789840698,
        -3.5644944773594034e-08,
        0.8914175033569336
      ],
      "groups": [],
      "impact_r": 0.021239855817285935,
      "name": "CMS_eff_tau",
      "prefit": [
        -0.9999999999999999,
        0.0,
        0.9999999999999999
      ],
      "r": [
        -0.021239852532744408,
        3.2845415276483436e-09,
        0.020699618384242058
      ],
      "type": "Gaussian"
    },
    {
      "fit": [
        -0.9917985796928406,
        0.0,
        0.9914814829826355
      ],
      "groups": [],
      "impact_r": 0.0015553135890513659,
      "name": "CMS_lfv_et_etauh_2jet_gg_13TeV_Diboson_bin_7",
      "prefit": [
        -1.0,
        0.0,
        1.0
      ],
      "r": [
        -0.0013971502194181085,
        0.0,
        0.0015553135890513659
      ],
      "type": "Gaussian"
    },
    {
      "fit": [
        -0.9921438694000244,
        0.0,
        0.9918614029884338
      ],
      "groups": [],
      "impact_r": 0.0002931881172116846,
      "name": "CMS_lfv_et_etauh_2jet_gg_13TeV_Diboson_bin_8",
      "prefit": [
        -1.0,
        0.0,
        1.0
      ],
      "r": [
        -0.0002756462781690061,
        0.0,
        0.0002931881172116846
      ],
      "type": "Gaussian"
    },
    {
      "fit": [
        -0.9920995831489563,
        0.0,
        0.9919020533561707
      ],
      "groups": [],
      "impact_r": 0.003917604219168425,
      "name": "CMS_lfv_et_etauh_2jet_gg_13TeV_Diboson_bin_9",
      "prefit": [
        -1.0,
        0.0,
        1.0
      ],
      "r": [
        -0.0003264712286181748,
        0.0,
        0.003917604219168425
      ],
      "type": "Gaussian"
    },
    {
      "fit": [
        -0.8381735682487488,
        0.0,
        0.85776686668396
      ],
      "groups": [],
      "impact_r": 0.005990911275148392,
      "name": "CMS_lfv_et_etauh_2jet_gg_13TeV_Fakes_bin_1",
      "prefit": [
        -1.0,
        0.0,
        1.0
      ],
      "r": [
        -0.003738677129149437,
        0.0,
        0.005990911275148392
      ],
      "type": "Gaussian"
    },
    {
      "fit": [
        -0.799334704875946,
        0.0,
        0.8116871118545532
      ],
      "groups": [],
      "impact_r": 0.128046914935112,
      "name": "CMS_lfv_et_etauh_2jet_gg_13TeV_Fakes_bin_10",
      "prefit": [
        -1.0,
        0.0,
        1.0
      ],
      "r": [
        0.128046914935112,
        0.0,
        -0.10128605365753174
      ],
      "type": "Gaussian"
    },
    {
      "fit": [
        -0.968019425868988,
        -2.9862952111159302e-09,
        0.9673219919204712
      ],
      "groups": [],
      "impact_r": 0.1853717090595719,
      "name": "CMS_lfv_et_etauh_2jet_gg_13TeV_Fakes_bin_13",
      "prefit": [
        -1.0,
        0.0,
        1.0
      ],
      "r": [
        0.18537171185016632,
        2.7905944222084145e-09,
        -0.18379747867584229
      ],
      "type": "Gaussian"
    },
    {
      "fit": [
        -0.9603580832481384,
        0.0,
        0.9615969657897949
      ],
      "groups": [],
      "impact_r": 0.20903097093105316,
      "name": "CMS_lfv_et_etauh_2jet_gg_13TeV_TT_bin_13",
      "prefit": [
        -1.0,
        0.0,
        1.0
      ],
      "r": [
        0.20903097093105316,
        0.0,
        -0.2030341774225235
      ],
      "type": "Gaussian"
    },
    {
      "fit": [
        -0.9668661952018738,
        7.387769507261055e-09,
        0.9669281244277954
      ],
      "groups": [],
      "impact_r": 0.02025780009772049,
      "name": "CMS_lfv_et_etauh_2jet_gg_13TeV_ZTauTau_bin_2",
      "prefit": [
        -1.0,
        0.0,
        1.0
      ],
      "r": [
        -0.020257797092199326,
        3.005521165277969e-09,
        0.01999002695083618
      ],
      "type": "Gaussian"
    },
    {
      "fit": [
        -0.965605616569519,
        0.0,
        0.9625349640846252
      ],
      "groups": [],
      "impact_r": 0.12317200005054474,
      "name": "CMS_lfv_et_etauh_2jet_gg_13TeV_Zothers_bin_11",
      "prefit": [
        -1.0,
        0.0,
        1.0
      ],
      "r": [
        0.12285435944795609,
        0.0,
        -0.12317200005054474
      ],
      "type": "Gaussian"
    },
    {
      "fit": [
        -0.7574252486228943,
        0.0,
        0.8138650059700012
      ],
      "groups": [],
      "impact_r": 0.3955681324005127,
      "name": "CMS_lfv_et_etauh_2jet_gg_13TeV_Zothers_bin_12",
      "prefit": [
        -1.0,
        0.0,
        1.0
      ],
      "r": [
        0.3955681324005127,
        0.0,
        -0.32856613397598267
      ],
      "type": "Gaussian"
    },
    {
      "fit": [
        -0.9874521493911743,
        0.0,
        0.9877720475196838
      ],
      "groups": [],
      "impact_r": 0.0028716332744807005,
      "name": "CMS_lfv_et_etauh_2jet_gg_13TeV_Zothers_bin_3",
      "prefit": [
        -1.0,
        0.0,
        1.0
      ],
      "r": [
        -0.0012763572158291936,
        0.0,
        0.0028716332744807005
      ],
      "type": "Gaussian"
    },
    {
      "fit": [
        -0.9904223084449768,
        0.0,
        0.9902156591415405
      ],
      "groups": [],
      "impact_r": 0.010132472030818462,
      "name": "CMS_lfv_et_etauh_2jet_gg_13TeV_Zothers_bin_4",
      "prefit": [
        -1.0,
        0.0,
        1.0
      ],
      "r": [
        -0.009251849725842476,
        0.0,
        0.010132472030818462
      ],
      "type": "Gaussian"
    },
    {
      "fit": [
        -0.9941003918647766,
        -1.9534742712323805e-09,
        0.9943708181381226
      ],
      "groups": [],
      "impact_r": 1.030232367860151e-06,
      "name": "CMS_lfv_et_etauh_2jet_gg_13TeV_ggH_htt_bin_5",
      "prefit": [
        -1.0,
        0.0,
        1.0
      ],
      "r": [
        1.032966451930406e-06,
        2.734084070254994e-09,
        -1.003171405500325e-06
      ],
      "type": "Gaussian"
    },
    {
      "fit": [
        -0.9613049030303955,
        0.0,
        0.961005687713623
      ],
      "groups": [],
      "impact_r": 0.02599923685193062,
      "name": "CMS_lumi_13TeV",
      "prefit": [
        -0.9999999999999999,
        0.0,
        0.9999999999999999
      ],
      "r": [
        0.02599923685193062,
        0.0,
        -0.024981116876006126
      ],
      "type": "Gaussian"
    },
    {
      "fit": [
        -0.9032357335090637,
        0.0,
        0.9672567844390869
      ],
      "groups": [],
      "impact_r": 0.013422817923128605,
      "name": "CMS_scale_efaketau_1prong1pizero_13TeV",
      "prefit": [
        -1.0,
        0.0,
        1.0
      ],
      "r": [
        -0.007773745805025101,
        0.0,
        -0.013422817923128605
      ],
      "type": "Gaussian"
    },
    {
      "fit": [
        -0.9915460348129272,
        3.800617598415101e-09,
        0.992719292640686
      ],
      "groups": [],
      "impact_r": 0.006122929373304942,
      "name": "CMS_scale_efaketau_1prong_13TeV",
      "prefit": [
        -1.0,
        0.0,
        1.0
      ],
      "r": [
        0.006122932303696871,
        2.9303919291123748e-09,
        0.003147338517010212
      ],
      "type": "Gaussian"
    },
    {
      "fit": [
        -0.8326245546340942,
        0.0,
        0.9249393343925476
      ],
      "groups": [],
      "impact_r": 0.12324906140565872,
      "name": "CMS_scale_t_1prong1pizero_13TeV",
      "prefit": [
        -1.0,
        0.0,
        1.0
      ],
      "r": [
        0.04732963442802429,
        0.0,
        -0.12324906140565872
      ],
      "type": "Gaussian"
    },
    {
      "fit": [
        -0.8595458269119263,
        -3.120302949355391e-08,
        0.8479492664337158
      ],
      "groups": [],
      "impact_r": 0.19957717986390922,
      "name": "CMS_scale_t_1prong_13TeV",
      "prefit": [
        -1.0,
        0.0,
        1.0
      ],
      "r": [
        0.1568032205104828,
        2.6674475961385724e-09,
        0.1995771825313568
      ],
      "type": "Gaussian"
    },
    {
      "fit": [
        -0.8587390184402466,
        0.0,
        0.9135202169418335
      ],
      "groups": [],
      "impact_r": 0.11914614588022232,
      "name": "CMS_scale_t_3prong_13TeV",
      "prefit": [
        -1.0,
        0.0,
        1.0
      ],
      "r": [
        0.11914614588022232,
        0.0,
        0.08557457476854324
      ],
      "type": "Gaussian"
    },
    {
      "fit": [
        -0.9938711524009705,
        0.0,
        0.9943512082099915
      ],
      "groups": [],
      "impact_r": 0.0005669281235896051,
      "name": "QCDScale_ggH",
      "prefit": [
        -0.9999999999999999,
        0.0,
        0.9999999999999999
      ],
      "r": [
        0.0005669281235896051,
        0.0,
        -0.0005506390007212758
      ],
      "type": "Gaussian"
    },
    {
      "fit": [
        -0.9938669800758362,
        -1.0304912478886763e-09,
        0.9943556189537048
      ],
      "groups": [],
      "impact_r": 1.0249046937360617e-05,
      "name": "QCDScale_qqH",
      "prefit": [
        -0.9999999999999999,
        0.0,
        0.9999999999999999
      ],
      "r": [
        1.0251244930259418e-05,
        2.197992898800294e-09,
        -1.0239068615192082e-05
      ],
      "type": "Gaussian"
    },
    {
      "fit": [
        -0.993867039680481,
        5.348015363892955e-10,
        0.9943555593490601
      ],
      "groups": [],
      "impact_r": 7.339729776845161e-05,
      "name": "acceptance_pdf_gg",
      "prefit": [
        -0.9999999999999999,
        0.0,
        0.9999999999999999
      ],
      "r": [
        -7.30264000594616e-05,
        2.7227144983044127e-09,
        7.340002048294991e-05
      ],
      "type": "Gaussian"
    },
    {
      "fit": [
        -0.9938669800758362,
        0.0,
        0.9943556189537048
      ],
      "groups": [],
      "impact_r": 3.8970021705608815e-05,
      "name": "acceptance_pdf_vbf",
      "prefit": [
        -0.9999999999999999,
        0.0,
        0.9999999999999999
      ],
      "r": [
        -3.8970021705608815e-05,
        0.0,
        3.860465585603379e-05
      ],
      "type": "Gaussian"
    },
    {
      "fit": [
        -0.9938697218894958,
        1.5487522375678964e-09,
        0.9943529963493347
      ],
      "groups": [],
      "impact_r": 0.00045024178626551503,
      "name": "acceptance_scale_gg",
      "prefit": [
        -0.9999999999999999,
        0.0,
        0.9999999999999999
      ],
      "r": [
        -0.0004395031137391925,
        2.4162458700516254e-09,
        0.0004502442025113851
      ],
      "type": "Gaussian"
    },
    {
      "fit": [
        -0.9938669800758362,
        -5.60695490037233e-10,
        0.9943556189537048
      ],
      "groups": [],
      "impact_r": 2.625639062614482e-06,
      "name": "acceptance_scale_vbf",
      "prefit": [
        -0.9999999999999999,
        0.0,
        0.9999999999999999
      ],
      "r": [
        -2.49911863647867e-06,
        1.0645017312072014e-08,
        2.636284079926554e-06
      ],
      "type": "Gaussian"
    },
    {
      "fit": [
        -0.9939792156219482,
        0.0,
        0.9942299723625183
      ],
      "groups": [],
      "impact_r": 0.0029602234717458487,
      "name": "norm_Diboson",
      "prefit": [
        -0.9999999999999999,
        0.0,
        0.9999999999999999
      ],
      "r": [
        0.0029602234717458487,
        0.0,
        -0.0029468636494129896
      ],
      "type": "Gaussian"
    },
    {
      "fit": [
        -0.9939792156219482,
        0.0,
        0.9942299723625183
      ],
      "groups": [],
      "impact_r": 0.0029601948335766792,
      "name": "norm_Diboson_etauh_2jet_gg",
      "prefit": [
        -0.9999999999999999,
        0.0,
        0.9999999999999999
      ],
      "r": [
        0.0029601948335766792,
        0.0,
        -0.002946888329461217
      ],
      "type": "Gaussian"
    },
    {
      "fit": [
        -0.993260383605957,
        0.0,
        0.9939958453178406
      ],
      "groups": [],
      "impact_r": 0.008453314192593098,
      "name": "norm_T",
      "prefit": [
        -0.9999999999999999,
        0.0,
        0.9999999999999999
      ],
      "r": [
        0.008075789548456669,
        0.0,
        -0.008453314192593098
      ],
      "type": "Gaussian"
    },
    {
      "fit": [
        -0.892708957195282,
        0.0,
        0.8791338801383972
      ],
      "groups": [],
      "impact_r": 0.0809100940823555,
      "name": "norm_TT",
      "prefit": [
        -0.9999999999999999,
        0.0,
        0.9999999999999999
      ],
      "r": [
        0.07666121423244476,
        0.0,
        -0.0809100940823555
      ],
      "type": "Gaussian"
    },
    {
      "fit": [
        -0.968785285949707,
        -3.4555938555058674e-08,
        0.9664737582206726
      ],
      "groups": [],
      "impact_r": 0.03727197136185545,
      "name": "norm_TT_etauh_2jet_gg",
      "prefit": [
        -0.9999999999999999,
        0.0,
        0.9999999999999999
      ],
      "r": [
        0.03677085414528847,
        2.3414887806438855e-09,
        -0.03727196902036667
      ],
      "type": "Gaussian"
    },
    {
      "fit": [
        -0.993260383605957,
        0.0,
        0.9939958453178406
      ],
      "groups": [],
      "impact_r": 0.00845750980079174,
      "name": "norm_T_etauh_2jet_gg",
      "prefit": [
        -0.9999999999999999,
        0.0,
        0.9999999999999999
      ],
      "r": [
        0.008073709905147552,
        0.0,
        -0.00845750980079174
      ],
      "type": "Gaussian"
    },
    {
      "fit": [
        -0.6259205937385559,
        0.0,
        0.5835100412368774
      ],
      "groups": [],
      "impact_r": 0.007670109160244465,
      "name": "norm_taufakes_etauhad",
      "prefit": [
        -0.9999999999999999,
        0.0,
        0.9999999999999999
      ],
      "r": [
        0.007670109160244465,
        0.0,
        -0.003255682997405529
      ],
      "type": "Gaussian"
    },
    {
      "fit": [
        -0.951961100101471,
        -1.246862382231484e-07,
        0.9516596794128418
      ],
      "groups": [],
      "impact_r": 0.001456441059442426,
      "name": "norm_taufakes_etauhad_uncor_etauh_2jet_gg",
      "prefit": [
        -0.9999999999999999,
        0.0,
        0.9999999999999999
      ],
      "r": [
        0.0014564519515261054,
        1.0892083679436837e-08,
        -0.0012508061481639743
      ],
      "type": "Gaussian"
    },
    {
      "fit": [
        -0.9178593158721924,
        0.0,
        0.9093632102012634
      ],
      "groups": [],
      "impact_r": 0.16481482982635498,
      "name": "norm_zothers",
      "prefit": [
        -0.9999999999999999,
        0.0,
        0.9999999999999999
      ],
      "r": [
        0.16266164183616638,
        0.0,
        -0.16481482982635498
      ],
      "type": "Gaussian"
    },
    {
      "fit": [
        -0.9807451963424683,
        0.0,
        0.9792367219924927
      ],
      "groups": [],
      "impact_r": 0.06672722101211548,
      "name": "norm_zothers_etauh_2jet_gg",
      "prefit": [
        -0.9999999999999999,
        0.0,
        0.9999999999999999
      ],
      "r": [
        0.06640210747718811,
        0.0,
        -0.06672722101211548
      ],
      "type": "Gaussian"
    },
    {
      "fit": [
        -0.8539518713951111,
        0.0,
        0.8439235091209412
      ],
      "groups": [],
      "impact_r": 0.17422686517238617,
      "name": "norm_ztt",
      "prefit": [
        -0.9999999999999999,
        0.0,
        0.9999999999999999
      ],
      "r": [
        -0.1640421450138092,
        0.0,
        0.17422686517238617
      ],
      "type": "Gaussian"
    },
    {
      "fit": [
        -0.9593600630760193,
        0.0,
        0.9578891396522522
      ],
      "groups": [],
      "impact_r": 0.07739976793527603,
      "name": "norm_ztt_etauh_2jet_gg",
      "prefit": [
        -0.9999999999999999,
        0.0,
        0.9999999999999999
      ],
      "r": [
        -0.07605850696563721,
        0.0,
        0.07739976793527603
      ],
      "type": "Gaussian"
    },
    {
      "fit": [
        -0.9938697814941406,
        2.158944134578178e-09,
        0.9943526983261108
      ],
      "groups": [],
      "impact_r": 0.0004655323861699756,
      "name": "pdf_Higgs_gg",
      "prefit": [
        -0.9999999999999999,
        0.0,
        0.9999999999999999
      ],
      "r": [
        0.0004655244993045926,
        -7.886865382999986e-09,
        -0.000454587658168748
      ],
      "type": "Gaussian"
    },
    {
      "fit": [
        -0.993867039680481,
        -1.4590346708587276e-09,
        0.9943556189537048
      ],
      "groups": [],
      "impact_r": 5.369609782057694e-05,
      "name": "pdf_Higgs_qq",
      "prefit": [
        -0.9999999999999999,
        0.0,
        0.9999999999999999
      ],
      "r": [
        5.298317410051823e-05,
        6.031696031527645e-09,
        -5.369006612454541e-05
      ],
      "type": "Gaussian"
    }
  ]
}